[{"id":"197","name":"","price":0,"cost":0,"element":"normal","isMagic":false,"weight":10,"exData":{}},{"id":"z196","name":"エンゼルアクス","price":7,"cost":0,"element":"normal","isMagic":false,"weight":10,"exData":{"iconUrl":"https://knq2stxhcdd03qgq.public.blob.vercel-storage.com/1053a7cf-74ac-4931-8209-2be6c393ad06?download=1"},"offensive":{"type":"attack","multiUse":false,"rate":1,"value":12}},{"id":"z195","name":"オーブ","price":3,"cost":0,"element":"light","isMagic":false,"weight":10,"exData":{"iconUrl":"https://knq2stxhcdd03qgq.public.blob.vercel-storage.com/1180d8e2-d425-403b-a0fa-f4f491f99730?download=1"},"offensive":{"type":"attack","multiUse":false,"rate":1,"value":9}},{"id":"z194","name":"氷山","price":0,"cost":20,"element":"water","isMagic":true,"weight":10,"exData":{"iconUrl":"https://knq2stxhcdd03qgq.public.blob.vercel-storage.com/15b5ced3-f658-4e42-8fbf-37804b273954?download=1"},"offensive":{"type":"attack","multiUse":false,"rate":0.75,"value":30}},{"id":"z193","name":"バーニングジャケット","price":5,"cost":0,"element":"fire","isMagic":false,"weight":10,"exData":{"iconUrl":"https://knq2stxhcdd03qgq.public.blob.vercel-storage.com/16ab6d1b-22c9-4e9b-975d-69a8b3520ade?download=1"},"defensive":{"type":"defense","multiUse":true,"value":9}},{"id":"z192","name":"絶景の槍","price":4,"cost":0,"element":"normal","isMagic":false,"weight":10,"exData":{"iconUrl":"https://knq2stxhcdd03qgq.public.blob.vercel-storage.com/193a05b3-73b7-4955-b7ce-a4bfca4059b4?download=1"},"offensive":{"type":"attack","multiUse":false,"rate":1,"value":12}},{"id":"z191","name":"フレアアクス","price":5,"cost":0,"element":"fire","isMagic":false,"weight":10,"exData":{"iconUrl":"https://knq2stxhcdd03qgq.public.blob.vercel-storage.com/1953fd93-684d-4409-a8bd-18b0ec0bdd52?download=1"},"offensive":{"type":"attack","multiUse":false,"rate":0.5,"value":10}},{"id":"z190","name":"精霊のぬいぐるみ","price":0,"cost":0,"element":"normal","isMagic":false,"weight":10,"exData":{"iconUrl":"https://knq2stxhcdd03qgq.public.blob.vercel-storage.com/1de08bd8-e89b-4dfa-8840-6f4179a6b13e?download=1"}},{"id":"z189","name":"雪崩","price":0,"cost":4,"element":"water","isMagic":true,"weight":10,"exData":{"iconUrl":"https://knq2stxhcdd03qgq.public.blob.vercel-storage.com/1dee1c10-a851-41d0-8113-46c546c5ca34?download=1"},"offensive":{"type":"attack","multiUse":false,"rate":0.65,"value":8}},{"id":"z188","name":"ダイヤモンドソード","price":7,"cost":0,"element":"wind","isMagic":false,"weight":10,"exData":{"iconUrl":"https://knq2stxhcdd03qgq.public.blob.vercel-storage.com/1e4424f6-6d4b-4e9b-b8f7-4ce51a8c296d?download=1"},"offensive":{"type":"attack","multiUse":false,"rate":1,"value":15}},{"id":"z187","name":"月光の兜","price":3,"cost":0,"element":"normal","isMagic":false,"weight":10,"exData":{"iconUrl":"https://knq2stxhcdd03qgq.public.blob.vercel-storage.com/1f0b8c14-d7c6-4b19-bcef-ca2f6ea634a5?download=1"},"defensive":{"type":"defense","multiUse":true,"value":10}},{"id":"z186","name":"バトルボール","price":2,"cost":0,"element":"normal","isMagic":false,"weight":10,"exData":{"iconUrl":"https://knq2stxhcdd03qgq.public.blob.vercel-storage.com/1fabe8ab-6ea6-4351-9220-a9b7a079c4ad?download=1"},"offensive":{"type":"attack","multiUse":true,"rate":1,"value":4}},{"id":"z185","name":"昇天弓","price":10,"cost":0,"element":"light","isMagic":false,"weight":10,"exData":{"iconUrl":"https://knq2stxhcdd03qgq.public.blob.vercel-storage.com/1ff8cace-e8a1-4b3c-a50b-54f2587f4032?download=1"},"offensive":{"type":"attack","multiUse":false,"rate":0.25,"value":1},"trap":{"type":"attack","multiUse":false,"rate":0.8,"value":50}},{"id":"z184","name":"ムチ","price":2,"cost":0,"element":"normal","isMagic":false,"weight":10,"exData":{"iconUrl":"https://knq2stxhcdd03qgq.public.blob.vercel-storage.com/210b32ce-8762-4a78-a5bf-c582a80e499c?download=1"},"offensive":{"type":"attack","multiUse":false,"rate":1,"value":2}},{"id":"z183","name":"矢","price":1,"cost":0,"element":"normal","isMagic":false,"weight":10,"exData":{"iconUrl":"https://knq2stxhcdd03qgq.public.blob.vercel-storage.com/216778d1-dd90-4e96-b400-950356e86ff5?download=1"},"offensive":{"type":"attack","multiUse":true,"rate":1,"value":1}},{"id":"z182","name":"キラキラシューズ","price":6,"cost":0,"element":"light","isMagic":false,"weight":10,"exData":{"iconUrl":"https://knq2stxhcdd03qgq.public.blob.vercel-storage.com/226f1773-90b5-43b2-bcbc-d9f84584d711?download=1"},"defensive":{"type":"defense","multiUse":true,"value":6}},{"id":"z181","name":"燃えムチ","price":2,"cost":0,"element":"fire","isMagic":false,"weight":10,"exData":{"iconUrl":"https://knq2stxhcdd03qgq.public.blob.vercel-storage.com/243850f1-855a-43c8-9534-680ca158126d?download=1"},"offensive":{"type":"attack","multiUse":false,"rate":1,"value":3}},{"id":"z180","name":"コアバリア","price":10,"cost":0,"element":"normal","isMagic":false,"weight":10,"exData":{"iconUrl":"https://knq2stxhcdd03qgq.public.blob.vercel-storage.com/26fc6758-45db-4c72-95ff-ff509eba98ba?download=1"},"defensive":{"type":"defense","multiUse":true,"value":13}},{"id":"z179","name":"地獄のハサミ","price":5,"cost":0,"element":"normal","isMagic":false,"weight":10,"exData":{"iconUrl":"https://knq2stxhcdd03qgq.public.blob.vercel-storage.com/28e1ed99-8d1c-40cb-8207-aa6516b5a25b?download=1"},"offensive":{"type":"attack","multiUse":false,"rate":1,"value":8}},{"id":"z178","name":"氷柱","price":1,"cost":0,"element":"water","isMagic":false,"weight":10,"exData":{"iconUrl":"https://knq2stxhcdd03qgq.public.blob.vercel-storage.com/29ff46c5-e2bf-41f4-963a-cc42981b581c?download=1"},"offensive":{"type":"attack","multiUse":true,"rate":1,"value":1}},{"id":"z177","name":"フレイムアーマー","price":5,"cost":0,"element":"fire","isMagic":false,"weight":10,"exData":{"iconUrl":"https://knq2stxhcdd03qgq.public.blob.vercel-storage.com/2a6f4e62-77e4-42b3-b749-dcf18801defb?download=1"},"defensive":{"type":"defense","multiUse":true,"value":12}},{"id":"z176","name":"恐怖の車輪","price":8,"cost":0,"element":"normal","isMagic":false,"weight":10,"exData":{"iconUrl":"https://knq2stxhcdd03qgq.public.blob.vercel-storage.com/2a936a40-886a-4eb5-9b4f-60981cae2b8a?download=1"},"offensive":{"type":"attack","multiUse":true,"rate":1,"value":11}},{"id":"z175","name":"月光の盾","price":10,"cost":0,"element":"normal","isMagic":false,"weight":10,"exData":{"iconUrl":"https://knq2stxhcdd03qgq.public.blob.vercel-storage.com/2b62fa12-66d0-40cb-b936-8dc3efde4c70?download=1"},"defensive":{"type":"defense","multiUse":true,"value":10}},{"id":"z174","name":"鋼の鎧","price":6,"cost":0,"element":"normal","isMagic":false,"weight":10,"exData":{"iconUrl":"https://knq2stxhcdd03qgq.public.blob.vercel-storage.com/2bbff903-4808-4f54-97f3-900f3254662d?download=1"},"defensive":{"type":"defense","multiUse":true,"value":9}},{"id":"z173","name":"植物杯","price":5,"cost":0,"element":"wood","isMagic":false,"weight":10,"exData":{"iconUrl":"https://knq2stxhcdd03qgq.public.blob.vercel-storage.com/2d04c25e-0f1b-4503-8fdb-30b5237cedd3?download=1"},"offensive":{"type":"attack","multiUse":false,"rate":0.75,"value":5}},{"id":"z172","name":"呪霊の羽","price":3,"cost":0,"element":"normal","isMagic":false,"weight":10,"exData":{"iconUrl":"https://knq2stxhcdd03qgq.public.blob.vercel-storage.com/2d654c2a-bf8c-495a-a6d6-130d35947d17?download=1"},"offensive":{"type":"attack","multiUse":true,"rate":1,"value":7}},{"id":"z171","name":"エルボーサック","price":3,"cost":0,"element":"normal","isMagic":false,"weight":10,"exData":{"iconUrl":"https://knq2stxhcdd03qgq.public.blob.vercel-storage.com/2dd1962f-1ac3-4bdc-abbe-a732dcb8b8f2?download=1"},"offensive":{"type":"attack","multiUse":false,"rate":1,"value":2},"defensive":{"type":"defense","multiUse":true,"value":5}},{"id":"z170","name":"弓","price":3,"cost":0,"element":"normal","isMagic":false,"weight":10,"exData":{"iconUrl":"https://knq2stxhcdd03qgq.public.blob.vercel-storage.com/2e324c75-e127-4b43-850f-846cbef53650?download=1"},"offensive":{"type":"attack","multiUse":true,"rate":1,"value":3}},{"id":"z169","name":"亡霊の法衣","price":5,"cost":0,"element":"normal","isMagic":false,"weight":10,"exData":{"iconUrl":"https://knq2stxhcdd03qgq.public.blob.vercel-storage.com/3088f4ba-788e-46c6-9d55-613de31eb88a?download=1"},"defensive":{"type":"defense","multiUse":true,"value":12}},{"id":"z168","name":"大地の兜","price":5,"cost":0,"element":"normal","isMagic":false,"weight":10,"exData":{"iconUrl":"https://knq2stxhcdd03qgq.public.blob.vercel-storage.com/3166ec2c-6162-48e9-b46d-532794084d12?download=1"},"defensive":{"type":"defense","multiUse":false,"value":6}},{"id":"z167","name":"グラビティメイス","price":3,"cost":0,"element":"normal","isMagic":false,"weight":10,"exData":{"iconUrl":"https://knq2stxhcdd03qgq.public.blob.vercel-storage.com/32847a85-9dc6-43a8-bcca-12f4ac1d50b7?download=1"},"offensive":{"type":"attack","multiUse":false,"rate":1,"value":11}},{"id":"z166","name":"独楽コンバット","price":5,"cost":0,"element":"normal","isMagic":false,"weight":10,"exData":{"iconUrl":"https://knq2stxhcdd03qgq.public.blob.vercel-storage.com/32e04249-db35-4288-afde-899fb72d9413?download=1"},"offensive":{"type":"attack","multiUse":true,"rate":1,"value":13}},{"id":"z165","name":"ミステリージュース","price":1,"cost":0,"element":"normal","isMagic":false,"weight":10,"exData":{"iconUrl":"https://knq2stxhcdd03qgq.public.blob.vercel-storage.com/348adfd6-e0f5-44c0-b6f0-e5ff4a92ad6d?download=1"},"offensive":{"type":"heal","healType":"hp","value":10}},{"id":"z164","name":"火の粉袋","price":1,"cost":0,"element":"fire","isMagic":false,"weight":10,"exData":{"iconUrl":"https://knq2stxhcdd03qgq.public.blob.vercel-storage.com/354d9caa-28e1-43b9-85b3-d423167f56ca?download=1"},"offensive":{"type":"attack","multiUse":false,"rate":0.75,"value":2}},{"id":"z163","name":"ファイヤークロスボウ","price":5,"cost":0,"element":"fire","isMagic":false,"weight":10,"exData":{"iconUrl":"https://knq2stxhcdd03qgq.public.blob.vercel-storage.com/36128f48-bf89-4b48-b87c-628be10d5eb7?download=1"},"offensive":{"type":"attack","multiUse":true,"rate":1,"value":5}},{"id":"z162","name":"ゴムの弓","price":5,"cost":0,"element":"lightning","isMagic":false,"weight":10,"exData":{"iconUrl":"https://knq2stxhcdd03qgq.public.blob.vercel-storage.com/36df860e-6852-4d6c-84df-0ea7a390e00f?download=1"},"offensive":{"type":"attack","multiUse":true,"rate":1,"value":3}},{"id":"z161","name":"銅のこん棒","price":3,"cost":0,"element":"normal","isMagic":false,"weight":10,"exData":{"iconUrl":"https://knq2stxhcdd03qgq.public.blob.vercel-storage.com/370c2134-0bd4-427e-96f6-9b42590ecdf2?download=1"},"offensive":{"type":"attack","multiUse":false,"rate":1,"value":1}},{"id":"z160","name":"封印の壺","price":0,"cost":0,"element":"normal","isMagic":false,"weight":10,"exData":{"iconUrl":"https://knq2stxhcdd03qgq.public.blob.vercel-storage.com/371eb2ee-5e55-492b-9695-fcd933891d8a?download=1"}},{"id":"z159","name":"虹のカーテン","price":10,"cost":0,"element":"light","isMagic":false,"weight":10,"exData":{"iconUrl":"https://knq2stxhcdd03qgq.public.blob.vercel-storage.com/38162b79-32eb-4c74-9884-dc9c936bdbf6?download=1"},"defensive":{"type":"defense","multiUse":true,"value":15}},{"id":"z158","name":"エンゼルアクス","price":5,"cost":0,"element":"normal","isMagic":false,"weight":10,"exData":{"iconUrl":"https://knq2stxhcdd03qgq.public.blob.vercel-storage.com/3830eb15-16a1-408c-9116-9abf0392e9b7?download=1"},"offensive":{"type":"attack","multiUse":false,"rate":1,"value":14}},{"id":"z157","name":"覇気","price":0,"cost":6,"element":"normal","isMagic":true,"weight":10,"exData":{"iconUrl":"https://knq2stxhcdd03qgq.public.blob.vercel-storage.com/38ff71ac-6a24-410b-aa5b-e6c475896f6c?download=1"},"offensive":{"type":"attack","multiUse":false,"rate":1,"value":10}},{"id":"z156","name":"大地のくつ","price":3,"cost":0,"element":"stone","isMagic":false,"weight":10,"exData":{"iconUrl":"https://knq2stxhcdd03qgq.public.blob.vercel-storage.com/3a35875b-19c3-4d0e-8195-a5442c62db34?download=1"},"defensive":{"type":"defense","multiUse":true,"value":4}},{"id":"z155","name":"ライトニングブレード","price":10,"cost":0,"element":"light","isMagic":false,"weight":10,"exData":{"iconUrl":"https://knq2stxhcdd03qgq.public.blob.vercel-storage.com/3af9ee1b-9c78-4a50-a78e-dd39b5a6fad4?download=1"},"offensive":{"type":"attack","multiUse":false,"rate":1,"value":11}},{"id":"z154","name":"疾風剣","price":6,"cost":0,"element":"normal","isMagic":false,"weight":10,"exData":{"iconUrl":"https://knq2stxhcdd03qgq.public.blob.vercel-storage.com/3b164ab5-5e53-46e8-9479-1748afbde1b6?download=1"},"offensive":{"type":"attack","multiUse":false,"rate":1,"value":7}},{"id":"z153","name":"こづち","price":5,"cost":0,"element":"wind","isMagic":false,"weight":10,"exData":{"iconUrl":"https://knq2stxhcdd03qgq.public.blob.vercel-storage.com/3d08cd28-13fb-4820-afdc-a895544a51da?download=1"},"offensive":{"type":"attack","multiUse":false,"rate":1,"value":5}},{"id":"z152","name":"キラーフォーク","price":5,"cost":0,"element":"dark","isMagic":false,"weight":10,"exData":{"iconUrl":"https://knq2stxhcdd03qgq.public.blob.vercel-storage.com/407c725a-e45e-4435-9908-471a59a34a44?download=1"},"offensive":{"type":"attack","multiUse":false,"rate":1,"value":5}},{"id":"z151","name":"悪魔の晩酌","price":5,"cost":0,"element":"normal","isMagic":false,"weight":10,"exData":{"iconUrl":"https://knq2stxhcdd03qgq.public.blob.vercel-storage.com/41ed3bf5-80c6-4125-9612-4fa9797a84b6?download=1"},"offensive":{"type":"heal","healType":"hp","value":25}},{"id":"z150","name":"デーモンハンド","price":5,"cost":0,"element":"dark","isMagic":false,"weight":10,"exData":{"iconUrl":"https://knq2stxhcdd03qgq.public.blob.vercel-storage.com/427af41c-cfa4-4870-beff-0d1f70ee6d22?download=1"},"offensive":{"type":"attack","multiUse":false,"rate":0.55,"value":5}},{"id":"z149","name":"精霊の足袋","price":10,"cost":0,"element":"normal","isMagic":false,"weight":10,"exData":{"iconUrl":"https://knq2stxhcdd03qgq.public.blob.vercel-storage.com/42b83fa5-0906-4cdb-b75c-cdde03cae541?download=1"},"defensive":{"type":"defense","multiUse":true,"value":8}},{"id":"z148","name":"革の服","price":2,"cost":0,"element":"normal","isMagic":false,"weight":10,"exData":{"iconUrl":"https://knq2stxhcdd03qgq.public.blob.vercel-storage.com/438974b0-acba-4391-b696-114e5492e17b?download=1"},"defensive":{"type":"defense","multiUse":true,"value":2}},{"id":"z147","name":"雨雲","price":0,"cost":4,"element":"water","isMagic":true,"weight":10,"exData":{"iconUrl":"https://knq2stxhcdd03qgq.public.blob.vercel-storage.com/43e76609-0b38-489c-b567-16411bb39f89?download=1"},"offensive":{"type":"attack","multiUse":false,"rate":0.35,"value":5}},{"id":"z146","name":"びっこみアクス","price":5,"cost":0,"element":"normal","isMagic":false,"weight":10,"exData":{"iconUrl":"https://knq2stxhcdd03qgq.public.blob.vercel-storage.com/44115eee-7bf6-4129-8c1e-dbc8d597393d?download=1"},"offensive":{"type":"attack","multiUse":false,"rate":1,"value":12}},{"id":"z145","name":"隕石","price":0,"cost":7,"element":"fire","isMagic":true,"weight":10,"exData":{"iconUrl":"https://knq2stxhcdd03qgq.public.blob.vercel-storage.com/44724107-8239-440b-a016-75a00034a3a8?download=1"},"offensive":{"type":"attack","multiUse":false,"rate":0.5,"value":12}},{"id":"z144","name":"神の盾","price":15,"cost":0,"element":"normal","isMagic":false,"weight":10,"exData":{"iconUrl":"https://knq2stxhcdd03qgq.public.blob.vercel-storage.com/46804c94-29e3-4558-ba28-4f1f0094d79b?download=1"},"defensive":{"type":"defense","multiUse":true,"value":30}},{"id":"z143","name":"金星の指輪","price":5,"cost":0,"element":"normal","isMagic":false,"weight":10,"exData":{"iconUrl":"https://knq2stxhcdd03qgq.public.blob.vercel-storage.com/4e834e78-af92-4151-bd5b-884cead6f276?download=1"},"offensive":{"type":"heal","healType":"gold","value":25}},{"id":"z142","name":"アイアンガントレット","price":3,"cost":0,"element":"normal","isMagic":false,"weight":10,"exData":{"iconUrl":"https://knq2stxhcdd03qgq.public.blob.vercel-storage.com/4ec8fda8-c461-4ff1-a1d6-f8ac43fe8649?download=1"},"defensive":{"type":"defense","multiUse":true,"value":3}},{"id":"z141","name":"ダークネスステッキ","price":10,"cost":25,"element":"normal","isMagic":false,"weight":10,"exData":{"iconUrl":"https://knq2stxhcdd03qgq.public.blob.vercel-storage.com/52681ca4-bc24-4a30-acb9-b3d46ee814bf?download=1"},"offensive":{"type":"attack","multiUse":false,"rate":1,"value":50}},{"id":"z140","name":"発火のワンド","price":5,"cost":0,"element":"fire","isMagic":false,"weight":10,"exData":{"iconUrl":"https://knq2stxhcdd03qgq.public.blob.vercel-storage.com/53e5a852-266f-4cf3-b785-93a69a63d328?download=1"},"offensive":{"type":"attack","multiUse":true,"rate":1,"value":8}},{"id":"z139","name":"エナジーヘルム","price":7,"cost":0,"element":"normal","isMagic":false,"weight":10,"exData":{"iconUrl":"https://knq2stxhcdd03qgq.public.blob.vercel-storage.com/548202a2-22dc-42ab-af0e-c4eb6770a1de?download=1"},"defensive":{"type":"defense","multiUse":true,"value":10}},{"id":"z138","name":"クロスボウ","price":2,"cost":0,"element":"normal","isMagic":false,"weight":10,"exData":{"iconUrl":"https://knq2stxhcdd03qgq.public.blob.vercel-storage.com/54a0d3f7-e668-4305-a306-96bbe6eca3a7?download=1"},"offensive":{"type":"attack","multiUse":true,"rate":1,"value":3}},{"id":"z137","name":"ソードシールド","price":5,"cost":0,"element":"normal","isMagic":false,"weight":10,"exData":{"iconUrl":"https://knq2stxhcdd03qgq.public.blob.vercel-storage.com/5544855e-a762-4438-a3d6-081a753a3009?download=1"},"offensive":{"type":"attack","multiUse":false,"rate":1,"value":10},"defensive":{"type":"defense","multiUse":true,"value":10}},{"id":"z136","name":"葉っぱ手裏剣","price":3,"cost":0,"element":"wood","isMagic":false,"weight":10,"exData":{"iconUrl":"https://knq2stxhcdd03qgq.public.blob.vercel-storage.com/57bdad47-013c-48a5-a229-a651fda6f3a8?download=1"},"offensive":{"type":"attack","multiUse":true,"rate":1,"value":3}},{"id":"z135","name":"ガラス細工","price":5,"cost":0,"element":"normal","isMagic":false,"weight":10,"exData":{"iconUrl":"https://knq2stxhcdd03qgq.public.blob.vercel-storage.com/5c3af4f2-4871-4eaa-924c-acd1820dbd38?download=1"},"defensive":{"type":"defense","multiUse":true,"value":9}},{"id":"z134","name":"鎖ガマ","price":3,"cost":0,"element":"normal","isMagic":false,"weight":10,"exData":{"iconUrl":"https://knq2stxhcdd03qgq.public.blob.vercel-storage.com/5fda6f7a-bccd-4d07-994f-6564aaa31778?download=1"},"offensive":{"type":"attack","multiUse":false,"rate":1,"value":5}},{"id":"z133","name":"大蛇の指輪","price":5,"cost":0,"element":"wind","isMagic":false,"weight":10,"exData":{"iconUrl":"https://knq2stxhcdd03qgq.public.blob.vercel-storage.com/5ffb76eb-04d7-48b5-b714-7589b8d89689?download=1"},"offensive":{"type":"attack","multiUse":true,"rate":0.6,"value":10},"defensive":{"type":"defense","multiUse":true,"value":10}},{"id":"z132","name":"木の盾","price":2,"cost":0,"element":"wood","isMagic":false,"weight":10,"exData":{"iconUrl":"https://knq2stxhcdd03qgq.public.blob.vercel-storage.com/62c9c42f-d34b-46a5-9ba8-419d75360cb2?download=1"},"defensive":{"type":"defense","multiUse":true,"value":3}},{"id":"z131","name":"鋼の兜","price":5,"cost":0,"element":"normal","isMagic":false,"weight":10,"exData":{"iconUrl":"https://knq2stxhcdd03qgq.public.blob.vercel-storage.com/61e6a642-6efe-47d9-ae28-a89fdc2f7715?download=1"},"defensive":{"type":"defense","multiUse":true,"value":7}},{"id":"z130","name":"ジャスティスランス","price":5,"cost":0,"element":"light","isMagic":false,"weight":10,"exData":{"iconUrl":"https://knq2stxhcdd03qgq.public.blob.vercel-storage.com/6267bc35-a372-44bd-ade2-302ea87b27af?download=1"},"offensive":{"type":"attack","multiUse":false,"rate":1,"value":5}},{"id":"z129","name":"結晶板","price":2,"cost":0,"element":"stone","isMagic":false,"weight":10,"exData":{"iconUrl":"https://knq2stxhcdd03qgq.public.blob.vercel-storage.com/6151ed1a-e266-4c6b-b4d8-26659026ab51?download=1"},"defensive":{"type":"defense","multiUse":true,"value":3}},{"id":"z128","name":"ブルーフレイムアーマー","price":5,"cost":0,"element":"fire","isMagic":false,"weight":10,"exData":{"iconUrl":"https://knq2stxhcdd03qgq.public.blob.vercel-storage.com/6329681e-9602-4d5a-8721-e98ab7d28302?download=1"},"defensive":{"type":"defense","multiUse":true,"value":7}},{"id":"z127","name":"鬼の腰巻き","price":3,"cost":0,"element":"normal","isMagic":false,"weight":10,"exData":{"iconUrl":"https://knq2stxhcdd03qgq.public.blob.vercel-storage.com/64e8966c-9255-40e0-8841-eea2359504c4?download=1"},"defensive":{"type":"defense","multiUse":true,"value":4}},{"id":"z126","name":"邪念の胸当て","price":5,"cost":0,"element":"normal","isMagic":false,"weight":10,"exData":{"iconUrl":"https://knq2stxhcdd03qgq.public.blob.vercel-storage.com/66b81660-a5a8-4c0b-a3e8-d617f932fb8a?download=1"},"defensive":{"type":"defense","multiUse":true,"value":10}},{"id":"z125","name":"ドクロの鎧","price":7,"cost":0,"element":"normal","isMagic":false,"weight":10,"exData":{"iconUrl":"https://knq2stxhcdd03qgq.public.blob.vercel-storage.com/6865537b-282d-4799-bdb9-3bef7e4c4c1e?download=1"},"defensive":{"type":"defense","multiUse":true,"value":14}},{"id":"z124","name":"革の帽子","price":1,"cost":0,"element":"normal","isMagic":false,"weight":10,"exData":{"iconUrl":"https://knq2stxhcdd03qgq.public.blob.vercel-storage.com/6960a686-fd9d-440a-8c45-b681f694e9cd?download=1"},"defensive":{"type":"defense","multiUse":true,"value":1}},{"id":"z123","name":"吹き矢","price":1,"cost":0,"element":"normal","isMagic":false,"weight":10,"exData":{"iconUrl":"https://knq2stxhcdd03qgq.public.blob.vercel-storage.com/698487d4-6f74-4cb8-a763-79bf0c3c72c5?download=1"},"offensive":{"type":"attack","multiUse":true,"rate":1,"value":1}},{"id":"z122","name":"パワーハルベルト","price":4,"cost":0,"element":"normal","isMagic":false,"weight":10,"exData":{"iconUrl":"https://knq2stxhcdd03qgq.public.blob.vercel-storage.com/6aac03ab-bbcd-4f6c-a685-174c24144260?download=1"},"offensive":{"type":"attack","multiUse":false,"rate":1,"value":8}},{"id":"z121","name":"雪玉","price":5,"cost":0,"element":"water","isMagic":false,"weight":10,"exData":{"iconUrl":"https://knq2stxhcdd03qgq.public.blob.vercel-storage.com/6abe9cf2-8ad1-4623-a1dd-f746e7ee56fa?download=1"},"offensive":{"type":"attack","multiUse":false,"rate":0.6,"value":5}},{"id":"z120","name":"冥王の指輪","price":10,"cost":0,"element":"dark","isMagic":false,"weight":10,"exData":{"iconUrl":"https://knq2stxhcdd03qgq.public.blob.vercel-storage.com/6b3dee0a-ca94-40ed-9e80-24bdd168a97a?download=1"},"offensive":{"type":"attack","multiUse":false,"rate":0.8,"value":15}},{"id":"z119","name":"ファイナル刃","price":3,"cost":0,"element":"normal","isMagic":false,"weight":10,"exData":{"iconUrl":"https://knq2stxhcdd03qgq.public.blob.vercel-storage.com/6bec7e3e-700d-4823-90cd-d6448664aa64?download=1"},"offensive":{"type":"attack","multiUse":false,"rate":1,"value":8}},{"id":"z118","name":"煙幕","price":0,"cost":5,"element":"fire","isMagic":true,"weight":10,"exData":{"iconUrl":"https://knq2stxhcdd03qgq.public.blob.vercel-storage.com/704d0f72-a26d-4547-b593-33bdc88f0ba7?download=1"},"offensive":{"type":"attack","multiUse":false,"rate":0.75,"value":5}},{"id":"z117","name":"アイアンアーマー","price":3,"cost":0,"element":"normal","isMagic":false,"weight":10,"exData":{"iconUrl":"https://knq2stxhcdd03qgq.public.blob.vercel-storage.com/7137dc84-1740-4aee-bcec-e0f0006f1f92?download=1"},"defensive":{"type":"defense","multiUse":true,"value":5}},{"id":"z116","name":"月光の斧","price":3,"cost":0,"element":"normal","isMagic":false,"weight":10,"exData":{"iconUrl":"https://knq2stxhcdd03qgq.public.blob.vercel-storage.com/72a8beb6-034a-423c-9b84-06644413bfd9?download=1"},"offensive":{"type":"attack","multiUse":false,"rate":1,"value":10}},{"id":"z115","name":"火炎杯","price":5,"cost":0,"element":"fire","isMagic":false,"weight":10,"exData":{"iconUrl":"https://knq2stxhcdd03qgq.public.blob.vercel-storage.com/75ad33b8-9804-4fa1-809c-6f6f885dd995?download=1"},"offensive":{"type":"attack","multiUse":false,"rate":0.75,"value":4}},{"id":"z114","name":"武士の剣","price":5,"cost":0,"element":"normal","isMagic":false,"weight":10,"exData":{"iconUrl":"https://knq2stxhcdd03qgq.public.blob.vercel-storage.com/76b59014-5e17-4253-8907-40ae88086db4?download=1"},"offensive":{"type":"attack","multiUse":false,"rate":1,"value":5}},{"id":"z113","name":"不思議なドレス","price":10,"cost":0,"element":"light","isMagic":false,"weight":10,"exData":{"iconUrl":"https://knq2stxhcdd03qgq.public.blob.vercel-storage.com/7713e476-49f2-4fce-970e-dbf0bc392465?download=1"},"defensive":{"type":"defense","multiUse":true,"value":15}},{"id":"z112","name":"壊れかけの金槌","price":3,"cost":0,"element":"normal","isMagic":false,"weight":10,"exData":{"iconUrl":"https://knq2stxhcdd03qgq.public.blob.vercel-storage.com/7a4f6277-c553-4336-8fba-e8ba54095d72?download=1"},"offensive":{"type":"attack","multiUse":false,"rate":0.5,"value":8}},{"id":"z111","name":"とげベルト","price":3,"cost":0,"element":"normal","isMagic":false,"weight":10,"exData":{"iconUrl":"https://knq2stxhcdd03qgq.public.blob.vercel-storage.com/7a94af50-0021-4787-ac5e-c81487d55a91?download=1"},"offensive":{"type":"attack","multiUse":false,"rate":1,"value":5},"defensive":{"type":"defense","multiUse":true,"value":3}},{"id":"z110","name":"ドクロの盾","price":3,"cost":0,"element":"wind","isMagic":false,"weight":10,"exData":{"iconUrl":"https://knq2stxhcdd03qgq.public.blob.vercel-storage.com/7adf8517-635e-4cf2-b5b3-262871ed1809?download=1"},"defensive":{"type":"defense","multiUse":true,"value":10}},{"id":"z109","name":"エンゼルの帽子","price":7,"cost":0,"element":"normal","isMagic":false,"weight":10,"exData":{"iconUrl":"https://knq2stxhcdd03qgq.public.blob.vercel-storage.com/7c8bca2e-50a7-4f9a-b124-b353e59d558b?download=1"},"defensive":{"type":"defense","multiUse":true,"value":11}},{"id":"z108","name":"スカイハープン","price":5,"cost":0,"element":"normal","isMagic":false,"weight":10,"exData":{"iconUrl":"https://knq2stxhcdd03qgq.public.blob.vercel-storage.com/7d1387eb-447e-4693-b49c-737ef11cd8d5?download=1"},"offensive":{"type":"attack","multiUse":true,"rate":1,"value":7}},{"id":"z107","name":"アイスハンマー","price":3,"cost":0,"element":"water","isMagic":false,"weight":10,"exData":{"iconUrl":"https://knq2stxhcdd03qgq.public.blob.vercel-storage.com/7f114feb-5f0c-46ff-8510-8ce2ce4dc68c?download=1"},"offensive":{"type":"attack","multiUse":false,"rate":1,"value":5}},{"id":"z106","name":"樹脂の法衣","price":5,"cost":0,"element":"wind","isMagic":false,"weight":10,"exData":{"iconUrl":"https://knq2stxhcdd03qgq.public.blob.vercel-storage.com/807a8c8d-5fb0-4562-be56-23780d8725be?download=1"},"defensive":{"type":"defense","multiUse":true,"value":8}},{"id":"z105","name":"スカイブーツ","price":1,"cost":0,"element":"normal","isMagic":false,"weight":10,"exData":{"iconUrl":"https://knq2stxhcdd03qgq.public.blob.vercel-storage.com/80eeed83-2b6b-48fd-94b5-4874fd8f6b4c?download=1"},"defensive":{"type":"defense","multiUse":true,"value":3}},{"id":"z104","name":"ドラゴンクロウ","price":7,"cost":0,"element":"normal","isMagic":false,"weight":10,"exData":{"iconUrl":"https://knq2stxhcdd03qgq.public.blob.vercel-storage.com/828e4929-51f8-48f6-8bc5-9d0b47e7b1d7?download=1"},"offensive":{"type":"attack","multiUse":false,"rate":1,"value":14}},{"id":"z103","name":"絶車輪","price":3,"cost":0,"element":"normal","isMagic":false,"weight":10,"exData":{"iconUrl":"https://knq2stxhcdd03qgq.public.blob.vercel-storage.com/865d89af-c19c-41da-8d1c-5161aa02a0a6?download=1"},"offensive":{"type":"attack","multiUse":true,"rate":1,"value":7}},{"id":"z102","name":"ワンダーソード","price":3,"cost":0,"element":"normal","isMagic":false,"weight":10,"exData":{"iconUrl":"https://knq2stxhcdd03qgq.public.blob.vercel-storage.com/880afd69-3874-4160-997b-da392dcc1e97?download=1"},"offensive":{"type":"attack","multiUse":false,"rate":1,"value":10}},{"id":"z101","name":"とんかち","price":3,"cost":0,"element":"normal","isMagic":false,"weight":10,"exData":{"iconUrl":"https://knq2stxhcdd03qgq.public.blob.vercel-storage.com/8b1eebff-18f0-4b7a-b9f5-a6672d1e6a07?download=1"},"offensive":{"type":"attack","multiUse":false,"rate":1,"value":6}},{"id":"z100","name":"薔薇の貝殻","price":5,"cost":0,"element":"normal","isMagic":false,"weight":10,"exData":{"iconUrl":"https://knq2stxhcdd03qgq.public.blob.vercel-storage.com/8b954c8e-23b1-4e64-8706-d33677b34c88?download=1"},"offensive":{"type":"heal","healType":"hp","value":20}},{"id":"z99","name":"烈火シャワー","price":5,"cost":0,"element":"fire","isMagic":false,"weight":10,"exData":{"iconUrl":"https://knq2stxhcdd03qgq.public.blob.vercel-storage.com/8d8bca6a-8d8d-4f3b-b2e6-d5bc55c18f1a?download=1"},"offensive":{"type":"attack","multiUse":false,"rate":0.7,"value":7}},{"id":"z98","name":"スピア","price":5,"cost":0,"element":"wind","isMagic":false,"weight":10,"exData":{"iconUrl":"https://knq2stxhcdd03qgq.public.blob.vercel-storage.com/8d9a4519-8b15-4e37-bfe0-58c4033339d2?download=1"},"offensive":{"type":"attack","multiUse":false,"rate":1,"value":7}},{"id":"z97","name":"スノーマスク","price":5,"cost":0,"element":"water","isMagic":false,"weight":10,"exData":{"iconUrl":"https://knq2stxhcdd03qgq.public.blob.vercel-storage.com/8ea62bf6-cb07-46f5-8d54-453bff5125f7?download=1"},"defensive":{"type":"defense","multiUse":true,"value":8}},{"id":"z96","name":"草冠","price":1,"cost":0,"element":"wood","isMagic":false,"weight":10,"exData":{"iconUrl":"https://knq2stxhcdd03qgq.public.blob.vercel-storage.com/8eaa9bde-2f10-43f3-8e47-9f82aedf4f8f?download=1"},"defensive":{"type":"defense","multiUse":true,"value":1}},{"id":"z95","name":"琥珀の胸当て","price":7,"cost":0,"element":"wood","isMagic":false,"weight":10,"exData":{"iconUrl":"https://knq2stxhcdd03qgq.public.blob.vercel-storage.com/90c442c6-0530-4711-a52a-89738aa34a73?download=1"},"defensive":{"type":"defense","multiUse":true,"value":10}},{"id":"z94","name":"夜空のほうき","price":0,"cost":0,"element":"normal","isMagic":false,"weight":10,"exData":{"iconUrl":"https://knq2stxhcdd03qgq.public.blob.vercel-storage.com/92bb1380-ca56-47ca-bb76-7140db6fb334?download=1"}},{"id":"z93","name":"鬼のくつ","price":5,"cost":0,"element":"normal","isMagic":false,"weight":10,"exData":{"iconUrl":"https://knq2stxhcdd03qgq.public.blob.vercel-storage.com/940972a8-808a-437f-9d53-435a065c7c3e?download=1"},"offensive":{"type":"attack","multiUse":true,"rate":1,"value":5},"defensive":{"type":"defense","multiUse":true,"value":5}},{"id":"z92","name":"スカイヘルム","price":5,"cost":0,"element":"normal","isMagic":false,"weight":10,"exData":{"iconUrl":"https://knq2stxhcdd03qgq.public.blob.vercel-storage.com/95681c42-e0fb-46e0-aeb4-8fbee0d3fec5?download=1"},"defensive":{"type":"defense","multiUse":true,"value":9}},{"id":"z91","name":"ファイナル刃","price":3,"cost":0,"element":"normal","isMagic":false,"weight":10,"exData":{"iconUrl":"https://knq2stxhcdd03qgq.public.blob.vercel-storage.com/965d1980-543e-43f5-8d6c-9214c459b02a?download=1"},"offensive":{"type":"attack","multiUse":false,"rate":1,"value":8}},{"id":"z90","name":"輝きの欠片","price":3,"cost":0,"element":"light","isMagic":false,"weight":10,"exData":{"iconUrl":"https://knq2stxhcdd03qgq.public.blob.vercel-storage.com/98b6140f-d995-4393-beed-b2eb102c7393?download=1"},"offensive":{"type":"attack","multiUse":true,"rate":1,"value":3}},{"id":"z89","name":"木刀","price":1,"cost":0,"element":"wood","isMagic":false,"weight":10,"exData":{"iconUrl":"https://knq2stxhcdd03qgq.public.blob.vercel-storage.com/9996390a-a1a9-4493-bcbc-3111d0967f36?download=1"},"offensive":{"type":"attack","multiUse":false,"rate":1,"value":1}},{"id":"z88","name":"コアアーマー","price":5,"cost":0,"element":"normal","isMagic":false,"weight":10,"exData":{"iconUrl":"https://knq2stxhcdd03qgq.public.blob.vercel-storage.com/99c433ad-c1b2-4f5b-a898-d7dde50f9eda?download=1"},"defensive":{"type":"defense","multiUse":true,"value":6}},{"id":"z87","name":"稲妻","price":0,"cost":5,"element":"lightning","isMagic":true,"weight":10,"exData":{"iconUrl":"https://knq2stxhcdd03qgq.public.blob.vercel-storage.com/99ca4228-ac53-45f2-bd89-3044663f6fee?download=1"},"offensive":{"type":"attack","multiUse":false,"rate":0.25,"value":10}},{"id":"z86","name":"スカイシールド","price":6,"cost":0,"element":"normal","isMagic":false,"weight":10,"exData":{"iconUrl":"https://knq2stxhcdd03qgq.public.blob.vercel-storage.com/9bb78481-7b88-4c2a-ba82-fa5b1c04e22c?download=1"},"defensive":{"type":"defense","multiUse":true,"value":7}},{"id":"z85","name":"木星の指輪","price":5,"cost":0,"element":"wood","isMagic":false,"weight":10,"exData":{"iconUrl":"https://knq2stxhcdd03qgq.public.blob.vercel-storage.com/9cc58a4c-bdc1-4fd6-be48-0a9ad28114cd?download=1"},"offensive":{"type":"attack","multiUse":false,"rate":0.45,"value":16}},{"id":"z84","name":"セイバーロッド","price":5,"cost":0,"element":"normal","isMagic":false,"weight":10,"exData":{"iconUrl":"https://knq2stxhcdd03qgq.public.blob.vercel-storage.com/a1ec92f0-6c93-4964-89c7-2e50ab4a6df6?download=1"},"defensive":{"type":"defense","multiUse":true,"value":5},"offensive":{"type":"attack","multiUse":false,"rate":1,"value":3}},{"id":"z83","name":"エンゼルソード","price":5,"cost":0,"element":"normal","isMagic":false,"weight":10,"exData":{"iconUrl":"https://knq2stxhcdd03qgq.public.blob.vercel-storage.com/a2316b45-6688-4f47-aec7-c7049be16136?download=1"},"offensive":{"type":"attack","multiUse":false,"rate":1,"value":9}},{"id":"z82","name":"森の盾","price":5,"cost":0,"element":"wood","isMagic":false,"weight":10,"exData":{"iconUrl":"https://knq2stxhcdd03qgq.public.blob.vercel-storage.com/a4c46edf-50fa-4c83-ad92-1e6fd549bf4c?download=1"},"defensive":{"type":"defense","multiUse":true,"value":7}},{"id":"z81","name":"怨念の剣","price":8,"cost":0,"element":"lightning","isMagic":false,"weight":10,"exData":{"iconUrl":"https://knq2stxhcdd03qgq.public.blob.vercel-storage.com/a6fcde04-b9ff-4954-b6ba-52ce338e9427?download=1"},"offensive":{"type":"attack","multiUse":false,"rate":1,"value":9}},{"id":"z80","name":"霧の扇","price":5,"cost":0,"element":"water","isMagic":false,"weight":10,"exData":{"iconUrl":"https://knq2stxhcdd03qgq.public.blob.vercel-storage.com/a70f5bef-f509-4d60-bab9-d178068534ea?download=1"},"offensive":{"type":"attack","multiUse":false,"rate":0.5,"value":5}},{"id":"z79","name":"流星","price":0,"cost":7,"element":"light","isMagic":true,"weight":10,"exData":{"iconUrl":"https://knq2stxhcdd03qgq.public.blob.vercel-storage.com/aab685c1-5456-4342-8883-08a45bf7dff5?download=1"},"offensive":{"type":"attack","multiUse":false,"rate":1,"value":10}},{"id":"z78","name":"精霊の頭巾","price":10,"cost":0,"element":"normal","isMagic":false,"weight":10,"exData":{"iconUrl":"https://knq2stxhcdd03qgq.public.blob.vercel-storage.com/ab6bc034-2205-4c85-8c64-e94303284087?download=1"},"defensive":{"type":"defense","multiUse":true,"value":9}},{"id":"z77","name":"ライトソード","price":10,"cost":0,"element":"normal","isMagic":false,"weight":10,"exData":{"iconUrl":"https://knq2stxhcdd03qgq.public.blob.vercel-storage.com/ac4ab397-c87a-49ce-bde6-5d518ade75a1?download=1"},"offensive":{"type":"attack","multiUse":false,"rate":1,"value":12}},{"id":"z76","name":"死神の鎌","price":10,"cost":0,"element":"dark","isMagic":false,"weight":10,"exData":{"iconUrl":"https://knq2stxhcdd03qgq.public.blob.vercel-storage.com/ac90c3bb-e596-4fae-b2c5-15c2cdc91ff8?download=1"},"offensive":{"type":"attack","multiUse":false,"rate":0.8,"value":15}},{"id":"z75","name":"のこぶんぶん","price":5,"cost":0,"element":"normal","isMagic":false,"weight":10,"exData":{"iconUrl":"https://knq2stxhcdd03qgq.public.blob.vercel-storage.com/b044fb9f-2a80-4ee7-bff3-d9785627044f?download=1"},"offensive":{"type":"attack","multiUse":false,"rate":1,"value":6}},{"id":"z74","name":"海王の指輪","price":5,"cost":0,"element":"water","isMagic":false,"weight":10,"exData":{"iconUrl":"https://knq2stxhcdd03qgq.public.blob.vercel-storage.com/b12e753d-b17e-44e2-9e05-dc538cd3e6b2?download=1"},"offensive":{"type":"attack","multiUse":false,"rate":0.7,"value":15}},{"id":"z73","name":"いばらのムチ","price":3,"cost":0,"element":"wind","isMagic":false,"weight":10,"exData":{"iconUrl":"https://knq2stxhcdd03qgq.public.blob.vercel-storage.com/b1815fc8-33fb-42a6-8c63-e9764f14c8f6?download=1"},"offensive":{"type":"attack","multiUse":false,"rate":1,"value":3}},{"id":"z72","name":"あちちナイフ","price":3,"cost":0,"element":"fire","isMagic":false,"weight":10,"exData":{"iconUrl":"https://knq2stxhcdd03qgq.public.blob.vercel-storage.com/b23d61b9-a9f0-41d4-8386-beef54b97769?download=1"},"offensive":{"type":"attack","multiUse":false,"rate":1,"value":5}},{"id":"z71","name":"スタースタッフ","price":5,"cost":0,"element":"light","isMagic":false,"weight":10,"exData":{"iconUrl":"https://knq2stxhcdd03qgq.public.blob.vercel-storage.com/b6276d0e-628e-4de4-b294-b4f011bc9b6b?download=1"},"offensive":{"type":"attack","multiUse":false,"rate":1,"value":3}},{"id":"z70","name":"エンゼルアーマー","price":10,"cost":0,"element":"normal","isMagic":false,"weight":10,"exData":{"iconUrl":"https://knq2stxhcdd03qgq.public.blob.vercel-storage.com/b7419c5d-cc5e-4c3f-ab84-1652fe4bd6d0?download=1"},"defensive":{"type":"defense","multiUse":true,"value":15}},{"id":"z69","name":"亡者の剣のさや","price":5,"cost":0,"element":"normal","isMagic":false,"weight":10,"exData":{"iconUrl":"https://knq2stxhcdd03qgq.public.blob.vercel-storage.com/b77d7508-4acf-4e4e-8b38-328f95e29dd2?download=1"},"offensive":{"type":"attack","multiUse":false,"rate":1,"value":15},"defensive":{"type":"defense","multiUse":true,"value":5}},{"id":"z68","name":"金のこん棒","price":30,"cost":0,"element":"light","isMagic":false,"weight":10,"exData":{"iconUrl":"https://knq2stxhcdd03qgq.public.blob.vercel-storage.com/b79f8601-eb6a-4d53-804f-25bafaeddaa8?download=1"},"offensive":{"type":"attack","multiUse":false,"rate":1,"value":1}},{"id":"z67","name":"運命のキネ","price":5,"cost":0,"element":"light","isMagic":false,"weight":10,"exData":{"iconUrl":"https://knq2stxhcdd03qgq.public.blob.vercel-storage.com/b8283d14-5de5-4685-923f-705f4497b7d2?download=1"},"offensive":{"type":"attack","multiUse":false,"rate":1,"value":30}},{"id":"z66","name":"フレイムヘルム","price":5,"cost":0,"element":"fire","isMagic":false,"weight":10,"exData":{"iconUrl":"https://knq2stxhcdd03qgq.public.blob.vercel-storage.com/b9b29676-4b66-4975-8b64-90c8aa46a643?download=1"},"defensive":{"type":"defense","multiUse":true,"value":7}},{"id":"z65","name":"つるぎ焼き","price":2,"cost":0,"element":"stone","isMagic":false,"weight":10,"exData":{"iconUrl":"https://knq2stxhcdd03qgq.public.blob.vercel-storage.com/ba2bd64d-20e4-4be5-b660-03398f2c79c6?download=1"},"offensive":{"type":"attack","multiUse":false,"rate":1,"value":2}},{"id":"z64","name":"魔神の木馬","price":5,"cost":0,"element":"wood","isMagic":false,"weight":10,"exData":{"iconUrl":"https://knq2stxhcdd03qgq.public.blob.vercel-storage.com/bb02076b-215a-4233-b723-2dc7e57e94f2?download=1"},"offensive":{"type":"attack","multiUse":false,"rate":0.85,"value":10}},{"id":"z63","name":"ほむら巻","price":3,"cost":0,"element":"fire","isMagic":false,"weight":10,"exData":{"iconUrl":"https://knq2stxhcdd03qgq.public.blob.vercel-storage.com/bc573a13-8219-4f14-8555-e30d9813e44a?download=1"},"offensive":{"type":"attack","multiUse":false,"rate":1,"value":4},"defensive":{"type":"defense","multiUse":true,"value":4}},{"id":"z62","name":"新石器トマホーク","price":5,"cost":0,"element":"stone","isMagic":false,"weight":10,"exData":{"iconUrl":"https://knq2stxhcdd03qgq.public.blob.vercel-storage.com/bd85d203-05b0-46f8-ae8b-93e24e2ddc2b?download=1"},"offensive":{"type":"attack","multiUse":true,"rate":1,"value":7}},{"id":"z61","name":"天国草","price":5,"cost":0,"element":"normal","isMagic":false,"weight":10,"exData":{"iconUrl":"https://knq2stxhcdd03qgq.public.blob.vercel-storage.com/bec40d73-bc7d-4b35-8ae1-dd6d10e81bc0?download=1"},"offensive":{"type":"heal","healType":"mp","value":20}},{"id":"z60","name":"廃れかけの花","price":3,"cost":0,"element":"normal","isMagic":false,"weight":10,"exData":{"iconUrl":"https://knq2stxhcdd03qgq.public.blob.vercel-storage.com/bed37679-c89a-47d7-a072-ab04d6afb896?download=1"},"offensive":{"type":"heal","healType":"mp","value":10}},{"id":"z59","name":"いがナッツ","price":3,"cost":0,"element":"stone","isMagic":false,"weight":10,"exData":{"iconUrl":"https://knq2stxhcdd03qgq.public.blob.vercel-storage.com/bee19084-1eb1-4536-887a-1ab05a3c3d4b?download=1"},"offensive":{"type":"attack","multiUse":false,"rate":1,"value":3}},{"id":"z58","name":"暴れフレイル","price":3,"cost":0,"element":"normal","isMagic":false,"weight":10,"exData":{"iconUrl":"https://knq2stxhcdd03qgq.public.blob.vercel-storage.com/bf3a65c9-6b43-4969-9506-657f949c1dfd?download=1"},"offensive":{"type":"attack","multiUse":false,"rate":1,"value":14}},{"id":"z57","name":"エンゼルの小手","price":10,"cost":0,"element":"normal","isMagic":false,"weight":10,"exData":{"iconUrl":"https://knq2stxhcdd03qgq.public.blob.vercel-storage.com/c2759211-5a04-4275-9fae-9e7036b0bc3d?download=1"},"defensive":{"type":"defense","multiUse":true,"value":12}},{"id":"z56","name":"バーニングジャケット","price":5,"cost":0,"element":"fire","isMagic":false,"weight":10,"exData":{"iconUrl":"https://knq2stxhcdd03qgq.public.blob.vercel-storage.com/c6ca0855-3e14-4598-95b1-1a2bc8b846d7?download=1"},"defensive":{"type":"defense","multiUse":true,"value":8}},{"id":"z55","name":"鬼の小手","price":5,"cost":0,"element":"normal","isMagic":false,"weight":10,"exData":{"iconUrl":"https://knq2stxhcdd03qgq.public.blob.vercel-storage.com/c8cffd0c-5147-4410-bb08-8ff1613e0394?download=1"},"offensive":{"type":"attack","multiUse":true,"rate":1,"value":10},"defensive":{"type":"defense","multiUse":true,"value":5}},{"id":"z54","name":"天王の指輪","price":5,"cost":0,"element":"lightning","isMagic":false,"weight":10,"exData":{"iconUrl":"https://knq2stxhcdd03qgq.public.blob.vercel-storage.com/c9475591-de4e-4601-bc41-2bb21c1b1c64?download=1"},"offensive":{"type":"attack","multiUse":false,"rate":0.75,"value":20}},{"id":"z53","name":"影武者の剣","price":5,"cost":0,"element":"dark","isMagic":false,"weight":10,"exData":{"iconUrl":"https://knq2stxhcdd03qgq.public.blob.vercel-storage.com/cadd380a-38e7-44de-a27b-dfbd3fa0021e?download=1"},"offensive":{"type":"attack","multiUse":false,"rate":1,"value":5}},{"id":"z52","name":"火花の手袋","price":2,"cost":0,"element":"fire","isMagic":false,"weight":10,"exData":{"iconUrl":"https://knq2stxhcdd03qgq.public.blob.vercel-storage.com/cd765873-7447-4976-88c2-b7d211411abd?download=1"},"defensive":{"type":"defense","multiUse":true,"value":3}},{"id":"z51","name":"狼のカギ爪","price":5,"cost":0,"element":"wind","isMagic":false,"weight":10,"exData":{"iconUrl":"https://knq2stxhcdd03qgq.public.blob.vercel-storage.com/cd5a5086-1bd3-4b8f-8b22-ed0810baadec?download=1"},"offensive":{"type":"attack","multiUse":false,"rate":1,"value":5}},{"id":"z50","name":"スカイガントレット","price":3,"cost":0,"element":"normal","isMagic":false,"weight":10,"exData":{"iconUrl":"https://knq2stxhcdd03qgq.public.blob.vercel-storage.com/cb2e37e7-16a5-41a8-b606-cd835652adc3?download=1"},"defensive":{"type":"defense","multiUse":true,"value":3}},{"id":"z49","name":"アイスシールド","price":3,"cost":0,"element":"water","isMagic":false,"weight":10,"exData":{"iconUrl":"https://knq2stxhcdd03qgq.public.blob.vercel-storage.com/ce1528f7-114f-4e24-ac25-7ee12ae78813?download=1"},"defensive":{"type":"defense","multiUse":true,"value":6}},{"id":"z48","name":"六角凶","price":5,"cost":0,"element":"dark","isMagic":false,"weight":10,"exData":{"iconUrl":"https://knq2stxhcdd03qgq.public.blob.vercel-storage.com/ce44fa5a-4d57-4ef4-a98a-822ab47a24a0?download=1"},"offensive":{"type":"attack","multiUse":false,"rate":1,"value":7}},{"id":"z47","name":"水鉄砲","price":5,"cost":0,"element":"water","isMagic":false,"weight":10,"exData":{"iconUrl":"https://knq2stxhcdd03qgq.public.blob.vercel-storage.com/d25e531d-9bec-4a69-a4c4-00e4267d7391?download=1"},"offensive":{"type":"attack","multiUse":false,"rate":1,"value":3}},{"id":"z46","name":"銀のこん棒","price":5,"cost":0,"element":"normal","isMagic":false,"weight":10,"exData":{"iconUrl":"https://knq2stxhcdd03qgq.public.blob.vercel-storage.com/d34a68d0-b899-45c9-a6de-e763fe938279?download=1"},"offensive":{"type":"attack","multiUse":false,"rate":1,"value":5}},{"id":"z45","name":"大地の鎧","price":5,"cost":0,"element":"stone","isMagic":false,"weight":10,"exData":{"iconUrl":"https://knq2stxhcdd03qgq.public.blob.vercel-storage.com/d4eb1ff2-2c08-46c8-a072-782ac1c9ff34?download=1"},"defensive":{"type":"defense","multiUse":true,"value":6}},{"id":"z44","name":"発狂仮面","price":10,"cost":0,"element":"normal","isMagic":false,"weight":10,"exData":{"iconUrl":"https://knq2stxhcdd03qgq.public.blob.vercel-storage.com/d7040d55-c955-40e6-90e1-0fef5665606f?download=1"},"defensive":{"type":"defense","multiUse":true,"value":10}},{"id":"z43","name":"鋼の小手","price":6,"cost":0,"element":"normal","isMagic":false,"weight":10,"exData":{"iconUrl":"https://knq2stxhcdd03qgq.public.blob.vercel-storage.com/e14629dd-531b-4d40-b1c6-ed62ccc25bad?download=1"},"defensive":{"type":"defense","multiUse":true,"value":6}},{"id":"z42","name":"アクアシューズ","price":2,"cost":0,"element":"water","isMagic":false,"weight":10,"exData":{"iconUrl":"https://knq2stxhcdd03qgq.public.blob.vercel-storage.com/d8ea6680-1f21-40f7-ab1a-e758bbb58ada?download=1"},"defensive":{"type":"defense","multiUse":true,"value":2}},{"id":"z41","name":"アイスブーツ","price":3,"cost":0,"element":"water","isMagic":false,"weight":10,"exData":{"iconUrl":"https://knq2stxhcdd03qgq.public.blob.vercel-storage.com/d9681dda-db4d-42b9-b2c6-d9e486902f8a?download=1"},"defensive":{"type":"defense","multiUse":true,"value":3}},{"id":"z40","name":"ブーメラン","price":3,"cost":0,"element":"normal","isMagic":false,"weight":10,"exData":{"iconUrl":"https://knq2stxhcdd03qgq.public.blob.vercel-storage.com/c39428e8-350d-4469-abff-71b58fa1455f?download=1"},"offensive":{"type":"attack","multiUse":true,"rate":1,"value":3}},{"id":"z39","name":"punch","price":5,"cost":0,"element":"normal","isMagic":false,"weight":10,"exData":{"iconUrl":"https://knq2stxhcdd03qgq.public.blob.vercel-storage.com/c3f1307a-6343-4174-ae79-ecf0d19fb74e?download=1"},"offensive":{"type":"attack","multiUse":false,"rate":1,"value":20}},{"id":"z38","name":"岩石杯","price":6,"cost":0,"element":"stone","isMagic":false,"weight":10,"exData":{"iconUrl":"https://knq2stxhcdd03qgq.public.blob.vercel-storage.com/ddf6d666-ba82-492e-bf10-876c73b2eaef?download=1"},"offensive":{"type":"attack","multiUse":false,"rate":0.75,"value":4}},{"id":"z37","name":"悪霊の杖","price":15,"cost":0,"element":"normal","isMagic":false,"weight":10,"exData":{"iconUrl":"https://knq2stxhcdd03qgq.public.blob.vercel-storage.com/de3e8a0d-b523-4bec-a285-db1a7c66fb60?download=1"},"offensive":{"type":"attack","multiUse":false,"rate":1,"value":12}},{"id":"z36","name":"鋼の盾","price":5,"cost":0,"element":"normal","isMagic":false,"weight":10,"exData":{"iconUrl":"https://knq2stxhcdd03qgq.public.blob.vercel-storage.com/df84e4eb-61e8-4c51-ae2a-e8c95af08232?download=1"},"defensive":{"type":"defense","multiUse":true,"value":8}},{"id":"z35","name":"水竜一角","price":10,"cost":0,"element":"water","isMagic":false,"weight":10,"exData":{"iconUrl":"https://knq2stxhcdd03qgq.public.blob.vercel-storage.com/dfaaf63e-405b-4d29-904c-00d14a02c8c6?download=1"},"offensive":{"type":"attack","multiUse":false,"rate":1,"value":8}},{"id":"z34","name":"神の剣","price":30,"cost":0,"element":"normal","isMagic":false,"weight":10,"exData":{"iconUrl":"https://knq2stxhcdd03qgq.public.blob.vercel-storage.com/dff3ea66-06d9-4fe3-a6f1-766fb430381c?download=1"},"offensive":{"type":"attack","multiUse":false,"rate":1,"value":30}},{"id":"z33","name":"天王の指輪","price":10,"cost":0,"element":"lightning","isMagic":false,"weight":10,"exData":{"iconUrl":"https://knq2stxhcdd03qgq.public.blob.vercel-storage.com/e0b0d5c4-e907-4c9c-81b5-d8261008b7e4?download=1"}},{"id":"z32","name":"アイスヘルム","price":6,"cost":0,"element":"water","isMagic":false,"weight":10,"exData":{"iconUrl":"https://knq2stxhcdd03qgq.public.blob.vercel-storage.com/e0e37574-20a2-43f4-8531-bcd4a5709ef8?download=1"},"defensive":{"type":"defense","multiUse":true,"value":4}},{"id":"z31","name":"御神木の小手","price":5,"cost":0,"element":"wood","isMagic":false,"weight":10,"exData":{"iconUrl":"https://knq2stxhcdd03qgq.public.blob.vercel-storage.com/d72d24e9-9198-4cf9-8989-7352461afd2a?download=1"},"defensive":{"type":"defense","multiUse":true,"value":3}},{"id":"z30","name":"ブルーフレイムブーツ","price":5,"cost":0,"element":"fire","isMagic":false,"weight":10,"exData":{"iconUrl":"https://knq2stxhcdd03qgq.public.blob.vercel-storage.com/e1728053-b181-4c38-9070-4cb5ffe2d75c?download=1"},"defensive":{"type":"defense","multiUse":true,"value":3}},{"id":"z29","name":"火竜一角","price":10,"cost":0,"element":"fire","isMagic":false,"weight":10,"exData":{"iconUrl":"https://knq2stxhcdd03qgq.public.blob.vercel-storage.com/e26b4062-16d1-470b-ab26-0430a6eb6bf6?download=1"},"offensive":{"type":"attack","multiUse":false,"rate":1,"value":8}},{"id":"z28","name":"ダークオーブ","price":5,"cost":0,"element":"light","isMagic":false,"weight":10,"exData":{"iconUrl":"https://knq2stxhcdd03qgq.public.blob.vercel-storage.com/e46caf87-7f2f-4357-9997-655b876177cb?download=1"},"offensive":{"type":"attack","multiUse":false,"rate":0.7,"value":10}},{"id":"z27","name":"フレイムロッド","price":5,"cost":0,"element":"fire","isMagic":false,"weight":10,"exData":{"iconUrl":"https://knq2stxhcdd03qgq.public.blob.vercel-storage.com/e4ade440-7124-4c0e-8825-7c985eab451b?download=1"},"offensive":{"type":"attack","multiUse":false,"rate":1,"value":6}},{"id":"z26","name":"ミステリーポーション","price":3,"cost":0,"element":"normal","isMagic":false,"weight":10,"exData":{"iconUrl":"https://knq2stxhcdd03qgq.public.blob.vercel-storage.com/e538cbec-30b1-40b6-9e6c-76ff5f6bb9b1?download=1"},"offensive":{"type":"heal","healType":"hp","value":15}},{"id":"z25","name":"パイナポー","price":1,"cost":0,"element":"normal","isMagic":false,"weight":10,"exData":{"iconUrl":"https://knq2stxhcdd03qgq.public.blob.vercel-storage.com/e58114d6-1ed9-4851-8d9d-8b5c762e2f80?download=1"},"offensive":{"type":"heal","healType":"mp","value":10}},{"id":"z24","name":"炎巻","price":5,"cost":0,"element":"fire","isMagic":false,"weight":10,"exData":{"iconUrl":"https://knq2stxhcdd03qgq.public.blob.vercel-storage.com/e65868d6-85b9-44e2-b426-ac235e298f5a?download=1"},"offensive":{"type":"attack","multiUse":false,"rate":1,"value":5},"defensive":{"type":"defense","multiUse":true,"value":5}},{"id":"z23","name":"デーモンシールド","price":10,"cost":0,"element":"normal","isMagic":false,"weight":10,"exData":{"iconUrl":"https://knq2stxhcdd03qgq.public.blob.vercel-storage.com/e6de7d93-8419-4ea9-bd6f-ab2ee5968065?download=1"},"defensive":{"type":"defense","multiUse":true,"value":15}},{"id":"z22","name":"サイキックガード","price":5,"cost":0,"element":"normal","isMagic":false,"weight":10,"exData":{"iconUrl":"https://knq2stxhcdd03qgq.public.blob.vercel-storage.com/e78605dc-c256-4657-8c28-e05b6ba9173b?download=1"},"offensive":{"type":"attack","multiUse":true,"rate":1,"value":5}},{"id":"z21","name":"雨神刀","price":5,"cost":0,"element":"water","isMagic":false,"weight":10,"exData":{"iconUrl":"https://knq2stxhcdd03qgq.public.blob.vercel-storage.com/e8690069-aafe-434a-979d-231369adab97?download=1"},"offensive":{"type":"attack","multiUse":false,"rate":0.5,"value":10}},{"id":"z20","name":"松明","price":1,"cost":0,"element":"fire","isMagic":false,"weight":10,"exData":{"iconUrl":"https://knq2stxhcdd03qgq.public.blob.vercel-storage.com/ea4e1261-2120-42ad-862b-2aac066d7a34?download=1"},"offensive":{"type":"attack","multiUse":false,"rate":1,"value":3}},{"id":"z19","name":"ブラックホール","price":5,"cost":0,"element":"dark","isMagic":false,"weight":1,"exData":{"iconUrl":"https://knq2stxhcdd03qgq.public.blob.vercel-storage.com/ecbf8240-4172-4a5b-bb33-b900b22bbfc4?download=1"},"offensive":{"type":"attack","multiUse":false,"rate":0.81,"value":35}},{"id":"z18","name":"鉄板","price":5,"cost":0,"element":"normal","isMagic":false,"weight":10,"exData":{"iconUrl":"https://knq2stxhcdd03qgq.public.blob.vercel-storage.com/ecc1be90-2f0d-4b9f-8222-a7233aeb473a?download=1"},"offensive":{"type":"attack","multiUse":false,"rate":1,"value":5},"defensive":{"type":"defense","multiUse":true,"value":7}},{"id":"z17","name":"雷鳴","price":10,"cost":15,"element":"lightning","isMagic":true,"weight":10,"exData":{"iconUrl":"https://knq2stxhcdd03qgq.public.blob.vercel-storage.com/ee56eed6-875a-486e-bbfa-3574acec25d1?download=1"},"offensive":{"type":"attack","multiUse":false,"rate":0.8,"value":15}},{"id":"z16","name":"おばけ","price":15,"cost":0,"element":"dark","isMagic":false,"weight":5,"exData":{"iconUrl":"https://knq2stxhcdd03qgq.public.blob.vercel-storage.com/eec27682-d82a-4e92-a2d8-1df1f695a397?download=1"},"offensive":{"type":"attack","multiUse":false,"rate":0.75,"value":20}},{"id":"z15","name":"鬼の鎧","price":15,"cost":0,"element":"normal","isMagic":false,"weight":10,"exData":{"iconUrl":"https://knq2stxhcdd03qgq.public.blob.vercel-storage.com/efc22cb0-7481-42d8-9a0d-064f79e64e59?download=1"},"offensive":{"type":"attack","multiUse":true,"rate":1,"value":15},"defensive":{"type":"defense","multiUse":true,"value":10}},{"id":"z14","name":"デーモンソード","price":7,"cost":0,"element":"normal","isMagic":false,"weight":10,"exData":{"iconUrl":"https://knq2stxhcdd03qgq.public.blob.vercel-storage.com/efcdd2bc-c7ba-458b-9500-4675739a9687?download=1"},"offensive":{"type":"attack","multiUse":false,"rate":1,"value":12}},{"id":"z13","name":"稲妻ソード","price":10,"cost":0,"element":"light","isMagic":false,"weight":10,"exData":{"iconUrl":"https://knq2stxhcdd03qgq.public.blob.vercel-storage.com/f11443ef-5a4e-4f88-bebc-8726aa44bf1b?download=1"},"offensive":{"type":"attack","multiUse":false,"rate":0.4,"value":15}},{"id":"z12","name":"不吉な雫","price":1,"cost":0,"element":"normal","isMagic":false,"weight":10,"exData":{"iconUrl":"https://knq2stxhcdd03qgq.public.blob.vercel-storage.com/f2552a5e-297a-4e75-83d7-9b890c690dc7?download=1"},"offensive":{"type":"heal","healType":"hp","value":5}},{"id":"z11","name":"鬼の兜","price":7,"cost":0,"element":"normal","isMagic":false,"weight":10,"exData":{"iconUrl":"https://knq2stxhcdd03qgq.public.blob.vercel-storage.com/f2ba5f68-b035-40f4-b5d7-6e89df8b8ebd?download=1"},"offensive":{"type":"attack","multiUse":true,"rate":1,"value":10},"defensive":{"type":"defense","multiUse":true,"value":7}},{"id":"z10","name":"エナジーアーマー","price":10,"cost":0,"element":"normal","isMagic":false,"weight":10,"exData":{"iconUrl":"https://knq2stxhcdd03qgq.public.blob.vercel-storage.com/f31e8b14-8330-4a5e-b07d-57fee50ed9c7?download=1"},"defensive":{"type":"defense","multiUse":false,"value":11}},{"id":"z9","name":"スノーミトン","price":5,"cost":0,"element":"water","isMagic":false,"weight":10,"exData":{"iconUrl":"https://knq2stxhcdd03qgq.public.blob.vercel-storage.com/f4ff3852-fd43-4e17-888f-b10f78290451?download=1"},"defensive":{"type":"defense","multiUse":true,"value":7}},{"id":"z8","name":"ゴーストソード","price":5,"cost":0,"element":"normal","isMagic":false,"weight":10,"exData":{"iconUrl":"https://knq2stxhcdd03qgq.public.blob.vercel-storage.com/f6975522-1a8f-44cd-9ad9-6627373df579?download=1"},"offensive":{"type":"attack","multiUse":false,"rate":1,"value":8}},{"id":"z7","name":"毒キノコ","price":5,"cost":0,"element":"wood","isMagic":false,"weight":10,"exData":{"iconUrl":"https://knq2stxhcdd03qgq.public.blob.vercel-storage.com/f6ef5d7f-d744-4f5a-bf78-ec4818e32296?download=1"},"offensive":{"type":"attack","multiUse":false,"rate":0.5,"value":15}},{"id":"z6","name":"アイアンアーマー","price":7,"cost":0,"element":"normal","isMagic":false,"weight":10,"exData":{"iconUrl":"https://knq2stxhcdd03qgq.public.blob.vercel-storage.com/f71638b6-8e95-4114-8d3e-ea1e726d07a2?download=1"},"defensive":{"type":"defense","multiUse":true,"value":7}},{"id":"z5","name":"運命のウス","price":1,"cost":0,"element":"light","isMagic":false,"weight":10,"exData":{"iconUrl":"https://knq2stxhcdd03qgq.public.blob.vercel-storage.com/f896c5ab-fed7-4ed0-91dc-8c54287c6aca?download=1"}},{"id":"z4","name":"なぎなた","price":3,"cost":0,"element":"normal","isMagic":false,"weight":10,"exData":{"iconUrl":"https://knq2stxhcdd03qgq.public.blob.vercel-storage.com/fa57cac7-cfa5-4c18-b2e0-48345b5d74e1?download=1"},"offensive":{"type":"attack","multiUse":false,"rate":1,"value":7}},{"id":"z3","name":"岩のかけら","price":2,"cost":0,"element":"stone","isMagic":false,"weight":10,"exData":{"iconUrl":"https://knq2stxhcdd03qgq.public.blob.vercel-storage.com/fb6faacd-c6b8-43cd-8cd6-a5c61a51b725?download=1"},"defensive":{"type":"defense","multiUse":true,"value":2}},{"id":"z2","name":"城壁","price":0,"cost":6,"element":"normal","isMagic":true,"weight":10,"exData":{"iconUrl":"https://knq2stxhcdd03qgq.public.blob.vercel-storage.com/fbb0dceb-5157-44f6-8885-de5352d4fca6?download=1"},"defensive":{"type":"defense","multiUse":false,"value":9999999}},{"id":"z1","name":"","price":2,"cost":0,"element":"normal","isMagic":false,"weight":10,"exData":{"iconUrl":"https://knq2stxhcdd03qgq.public.blob.vercel-storage.com/fe088280-82bb-46eb-9d0e-9b37f3db6b3c?download=1"},"offensive":{"type":"attack","multiUse":false,"rate":1,"value":4}}]